huihuo_tool_kit/__init__.py
huihuo_tool_kit/excel_tool.py
tests/__init__.py
huihuo_tool_kit-0.1.0.dist-info/METADATA
huihuo_tool_kit-0.1.0.dist-info/WHEEL
huihuo_tool_kit-0.1.0.dist-info/entry_points.txt
huihuo_tool_kit-0.1.0.dist-info/top_level.txt
huihuo_tool_kit-0.1.0.dist-info/RECORD
