Metadata-Version: 2.1
Name: huihuo-tool-kit
Version: 0.1.0
Summary: huihuo tool kit
Home-page: https://github.com/hui-huo
Author: huihuo
Requires-Dist: build
